unwatermark/__init__.py
unwatermark/async_unwater.py
unwatermark/models.py
unwatermark/unwater.py
unwatermark-1.5.0.dist-info/LICENSE
unwatermark-1.5.0.dist-info/METADATA
unwatermark-1.5.0.dist-info/WHEEL
unwatermark-1.5.0.dist-info/top_level.txt
unwatermark-1.5.0.dist-info/RECORD
