Metadata-Version: 2.1
Name: unwatermark
Version: 1.5.0
Summary: A library for asynchronous and synchronous watermark removal from images using Unwatermark.ai
Home-page: https://github.com/FSystem88/unwatermark
Author: FSystem88
Author-email: ivan@fsystem88.ru
Classifier: Programming Language :: Python :: 3
Classifier: License :: OSI Approved :: MIT License
Classifier: Operating System :: OS Independent
Requires-Python: >=3.6
License-File: LICENSE
Requires-Dist: httpx
Requires-Dist: aiofiles
Requires-Dist: pydantic
